README.rst
setup.cfg
setup.py
pars_green/__init__.py
pars_green/pars_green_connector.py
pars_green.egg-info/PKG-INFO
pars_green.egg-info/SOURCES.txt
pars_green.egg-info/dependency_links.txt
pars_green.egg-info/requires.txt
pars_green.egg-info/top_level.txt