Metadata-Version: 1.1
Name: pars-green
Version: 1.2.1
Summary: Python Pars Green
Home-page: https://github.com/mhipo1364/pars-green
Author: Mohammad Torkianfar
Author-email: mhipo1364@gmail.com
License: MIT
Keywords: pars green soap
Platform: UNKNOWN
Classifier: Development Status :: 3 - Alpha
Classifier: Intended Audience :: Developers
Classifier: Topic :: Software Development :: Build Tools
Classifier: License :: OSI Approved :: MIT License
Classifier: Programming Language :: Python :: 3
Classifier: Programming Language :: Python :: 3.3
Classifier: Programming Language :: Python :: 3.4
Classifier: Programming Language :: Python :: 3.5
Classifier: Programming Language :: Python :: 2
Classifier: Programming Language :: Python :: 2.7
